<bibdata type="inbook" schema-version="v1.5.6">
  <fetched>2026-03-03</fetched>
  <title script="Latn" type="main">Culinary arts: Talent and their development.</title>
  <uri type="DOI">https://doi.org/10.1037/0000120-016</uri>
  <uri type="src">https://content.apa.org/books/16096-016</uri>
  <docidentifier type="DOI" primary="true">10.1037/0000120-016</docidentifier>
  <docidentifier type="ISBN" primary="false">1433829886</docidentifier>
  <docidentifier type="ISBN" primary="false">1433830388</docidentifier>
  <docidentifier type="ISBN" primary="false">9781433829888</docidentifier>
  <docidentifier type="ISBN" primary="false">9781433830389</docidentifier>
  <date type="issued">
    <on>2019</on>
  </date>
  <date type="published">
    <on>2019</on>
  </date>
  <contributor>
    <role type="author"/>
    <person>
      <name>
        <forename language="en" script="Latn">Laurent</forename>
        <surname language="en" script="Latn">Aron</surname>
      </name>
    </person>
  </contributor>
  <contributor>
    <role type="author"/>
    <person>
      <name>
        <forename language="en" script="Latn">Marion</forename>
        <surname language="en" script="Latn">Botella</surname>
      </name>
    </person>
  </contributor>
  <contributor>
    <role type="author"/>
    <person>
      <name>
        <forename language="en" script="Latn">Todd</forename>
        <surname language="en" script="Latn">Lubart</surname>
      </name>
    </person>
  </contributor>
  <contributor>
    <role type="publisher"/>
    <organization>
      <name>American Psychological Association</name>
    </organization>
  </contributor>
  <relation type="includedIn">
    <bibitem>
      <title>Psychology of high performance: Developing human potential into domain-specific talent.</title>
      <contributor>
        <role type="editor"/>
        <person>
          <name>
            <forename language="en" script="Latn">Rena F.</forename>
            <surname language="en" script="Latn">Subotnik</surname>
          </name>
        </person>
      </contributor>
      <contributor>
        <role type="editor"/>
        <person>
          <name>
            <forename language="en" script="Latn">Paula</forename>
            <surname language="en" script="Latn">Olszewski-Kubilius</surname>
          </name>
        </person>
      </contributor>
      <contributor>
        <role type="editor"/>
        <person>
          <name>
            <forename language="en" script="Latn">Frank C.</forename>
            <surname language="en" script="Latn">Worrell</surname>
          </name>
        </person>
      </contributor>
    </bibitem>
  </relation>
  <place>
    <city>Washington</city>
  </place>
  <extent>
    <locality type="page">
      <referenceFrom>345</referenceFrom>
      <referenceTo>359</referenceTo>
    </locality>
  </extent>
  <ext>
    <doctype>book-chapter</doctype>
  </ext>
</bibdata>
